elyra/__init__.py
elyra/_version.py
elyra/elyra_app.py
elyra/airflow/__init__.py
elyra/airflow/bootstrapper.py
elyra/airflow/operator.py
elyra/api/__init__.py
elyra/api/elyra.yaml
elyra/api/handlers.py
elyra/cli/__init__.py
elyra/cli/pipeline_app.py
elyra/cli/pipeline_app_utils.py
elyra/contents/__init__.py
elyra/contents/handlers.py
elyra/contents/parser.py
elyra/kfp/__init__.py
elyra/kfp/bootstrapper.py
elyra/metadata/__init__.py
elyra/metadata/error.py
elyra/metadata/handlers.py
elyra/metadata/manager.py
elyra/metadata/metadata.py
elyra/metadata/metadata_app.py
elyra/metadata/metadata_app_utils.py
elyra/metadata/schema.py
elyra/metadata/schemaspaces.py
elyra/metadata/schemasproviders.py
elyra/metadata/storage.py
elyra/metadata/schemas/airflow.json
elyra/metadata/schemas/code-snippet.json
elyra/metadata/schemas/kfp.json
elyra/metadata/schemas/local-directory-catalog.json
elyra/metadata/schemas/local-file-catalog.json
elyra/metadata/schemas/meta-schema.json
elyra/metadata/schemas/metadata-test.json
elyra/metadata/schemas/metadata-test2.json
elyra/metadata/schemas/runtime-image.json
elyra/metadata/schemas/url-catalog.json
elyra/pipeline/__init__.py
elyra/pipeline/catalog_connector.py
elyra/pipeline/component.py
elyra/pipeline/component_catalog.py
elyra/pipeline/component_metadata.py
elyra/pipeline/elyra_engine.py
elyra/pipeline/handlers.py
elyra/pipeline/parser.py
elyra/pipeline/pipeline.py
elyra/pipeline/pipeline_constants.py
elyra/pipeline/pipeline_definition.py
elyra/pipeline/processor.py
elyra/pipeline/properties.py
elyra/pipeline/registry.py
elyra/pipeline/runtime_type.py
elyra/pipeline/runtimes_metadata.py
elyra/pipeline/validation.py
elyra/pipeline/airflow/__init__.py
elyra/pipeline/airflow/airflow_component_parser.py
elyra/pipeline/airflow/airflow_metadata.py
elyra/pipeline/airflow/airflow_processor.py
elyra/pipeline/airflow/package_catalog_connector/README.md
elyra/pipeline/airflow/package_catalog_connector/__init__.py
odh_elyra-4.3.2.dist-info/METADATA
odh_elyra-4.3.2.dist-info/WHEEL
odh_elyra-4.3.2.dist-info/entry_points.txt
odh_elyra-4.3.2.dist-info/licenses/LICENSE
odh_elyra-4.3.2.dist-info/RECORD
