Metadata-Version: 2.4
Name: odh-elyra
Version: 4.3.2
Summary: Elyra provides AI Centric extensions to JupyterLab
Project-URL: Documentation, https://elyra.readthedocs.io/en/latest
Project-URL: Homepage, https://github.com/opendatahub-io/elyra
Maintainer: ODH IDE Maintainers
License-File: LICENSE
Classifier: License :: OSI Approved :: Apache Software License
Classifier: Operating System :: OS Independent
Classifier: Programming Language :: Python :: 3.9
Classifier: Programming Language :: Python :: 3.10
Classifier: Programming Language :: Python :: 3.11
Classifier: Programming Language :: Python :: 3.12
Classifier: Programming Language :: Python :: 3.13
Classifier: Topic :: Scientific/Engineering
Classifier: Topic :: Scientific/Engineering :: Artificial Intelligence
Classifier: Topic :: Software Development
Classifier: Topic :: Software Development :: Libraries
Classifier: Topic :: Software Development :: Libraries :: Python Modules
Requires-Python: >=3.9
Requires-Dist: appengine-python-standard
Requires-Dist: autopep8>=1.5.0
Requires-Dist: black>=22.8.0
Requires-Dist: click==8.1.8
Requires-Dist: colorama
Requires-Dist: deprecation
Requires-Dist: entrypoints>=0.3
Requires-Dist: jinja2>=3
Requires-Dist: jsonschema>=3.2.0
Requires-Dist: jupyter-client>=6.1.7
Requires-Dist: jupyter-core>=4.11.0
Requires-Dist: jupyter-events>=0.6.2
Requires-Dist: jupyter-packaging>=0.10
Requires-Dist: jupyter-resource-usage~=1.1.0
Requires-Dist: jupyter-server>=1.7.0
Requires-Dist: jupyterlab-git~=0.51.2
Requires-Dist: jupyterlab-lsp~=5.1.0
Requires-Dist: jupyterlab~=4.4
Requires-Dist: kfp-kubernetes>=1.0.0
Requires-Dist: kfp>=2.0.0
Requires-Dist: markupsafe>=2.1
Requires-Dist: minio!=7.2.1,>=7.0.0
Requires-Dist: nbclient>=0.10.0
Requires-Dist: nbconvert>=6.5.1
Requires-Dist: nbdime~=4.0.1
Requires-Dist: nbformat>=5.1.2
Requires-Dist: networkx>=2.5.1
Requires-Dist: papermill>=2.3.4
Requires-Dist: pygithub
Requires-Dist: python-lsp-server[all]>=1.11.0
Requires-Dist: pyyaml>=5.3.1
Requires-Dist: requests>=2.31
Requires-Dist: rfc3986-validator>=0.1.1
Requires-Dist: tornado>=6.1.0
Requires-Dist: traitlets>=4.3.2
Requires-Dist: typing-extensions<5,>=3.10
Requires-Dist: urllib3>=1.26.5
Requires-Dist: watchdog>=2.1.3
Requires-Dist: websocket-client
Requires-Dist: yaspin
Provides-Extra: all
Requires-Dist: elyra-examples-kfp-catalog; extra == 'all'
Requires-Dist: python-gitlab; extra == 'all'
Provides-Extra: dev
Requires-Dist: flake8-import-order>=0.18.1; extra == 'dev'
Requires-Dist: flake8-pyproject>=1.2.4; extra == 'dev'
Requires-Dist: flake8<7.2.0,>=3.5.0; extra == 'dev'
Provides-Extra: gitlab
Requires-Dist: python-gitlab; extra == 'gitlab'
Provides-Extra: kfp-examples
Requires-Dist: elyra-examples-kfp-catalog; extra == 'kfp-examples'
Provides-Extra: test
Requires-Dist: elyra-examples-kfp-catalog; extra == 'test'
Requires-Dist: git-python; extra == 'test'
Requires-Dist: importlib-resources; extra == 'test'
Requires-Dist: pytest-console-scripts; extra == 'test'
Requires-Dist: pytest-cov; extra == 'test'
Requires-Dist: pytest-jupyter; extra == 'test'
Requires-Dist: pytest-tornasync; extra == 'test'
Requires-Dist: pytest-virtualenv; extra == 'test'
Requires-Dist: pytest>=5.4.1; extra == 'test'
Requires-Dist: requests-mock; extra == 'test'
Requires-Dist: requests-unixsocket; extra == 'test'
